{
    "_links": {
        "self": {
            "href": "http:\/\/default\/en\/1\/content\/18?_format=hal_json"
        },
        "type": {
            "href": "http:\/\/drupal.org\/rest\/type\/group_content\/fut_open-group_node-fut_event"
        },
        "http:\/\/drupal.org\/rest\/relation\/group_content\/fut_open-group_node-fut_event\/gid": [
            {
                "href": "http:\/\/default\/nunc-group-sodales-vestibulum-consectetur-adipiscing-elit?_format=hal_json"
            }
        ],
        "http:\/\/drupal.org\/rest\/relation\/group_content\/fut_open-group_node-fut_event\/entity_id": [
            {
                "href": "http:\/\/default\/nunc-group-sodales-vestibulum-consectetur-adipiscing-elit\/events\/nisl-suscipit-adipiscing-bibendum-est-ultricies-integer-quis-auctor?_format=hal_json"
            }
        ],
        "http:\/\/drupal.org\/rest\/relation\/group_content\/fut_open-group_node-fut_event\/uid": [
            {
                "href": "http:\/\/default\/en\/user\/4?_format=hal_json",
                "lang": "en"
            }
        ]
    },
    "id": [
        {
            "value": 18
        }
    ],
    "uuid": [
        {
            "value": "8019c36d-292c-476a-b806-7a8fdda08875"
        }
    ],
    "langcode": [
        {
            "value": "en",
            "lang": "en"
        }
    ],
    "type": [
        {
            "target_id": "fut_open-group_node-fut_event"
        }
    ],
    "_embedded": {
        "http:\/\/drupal.org\/rest\/relation\/group_content\/fut_open-group_node-fut_event\/gid": [
            {
                "_links": {
                    "self": {
                        "href": "http:\/\/default\/nunc-group-sodales-vestibulum-consectetur-adipiscing-elit?_format=hal_json"
                    },
                    "type": {
                        "href": "http:\/\/drupal.org\/rest\/type\/group\/fut_open"
                    }
                },
                "uuid": [
                    {
                        "value": "5aae6242-97b2-4edd-b87d-02190849ce8d"
                    }
                ]
            }
        ],
        "http:\/\/drupal.org\/rest\/relation\/group_content\/fut_open-group_node-fut_event\/entity_id": [
            {
                "_links": {
                    "self": {
                        "href": "http:\/\/default\/nunc-group-sodales-vestibulum-consectetur-adipiscing-elit\/events\/nisl-suscipit-adipiscing-bibendum-est-ultricies-integer-quis-auctor?_format=hal_json"
                    },
                    "type": {
                        "href": "http:\/\/drupal.org\/rest\/type\/node\/fut_event"
                    }
                },
                "uuid": [
                    {
                        "value": "34584171-f4ca-4b9c-9c3b-08ff322c6285"
                    }
                ]
            }
        ],
        "http:\/\/drupal.org\/rest\/relation\/group_content\/fut_open-group_node-fut_event\/uid": [
            {
                "_links": {
                    "self": {
                        "href": "http:\/\/default\/en\/user\/4?_format=hal_json"
                    },
                    "type": {
                        "href": "http:\/\/drupal.org\/rest\/type\/user\/user"
                    }
                },
                "uuid": [
                    {
                        "value": "6ec394d7-6db0-4d6f-b62d-1e37bf7e18e0"
                    }
                ],
                "lang": "en"
            }
        ]
    },
    "label": [
        {
            "value": "Nisl suscipit adipiscing bibendum est ultricies integer quis auctor",
            "lang": "en"
        }
    ],
    "created": [
        {
            "value": "2019-07-25T09:54:30+00:00",
            "lang": "en",
            "format": "Y-m-d\\TH:i:sP"
        }
    ],
    "changed": [
        {
            "value": "2019-07-25T09:54:30+00:00",
            "lang": "en",
            "format": "Y-m-d\\TH:i:sP"
        }
    ],
    "path": [
        {
            "alias": "\/1\/content\/18",
            "pid": 31,
            "langcode": "en",
            "lang": "en"
        }
    ],
    "default_langcode": [
        {
            "value": true,
            "lang": "en"
        }
    ]
}