{
    "_links": {
        "self": {
            "href": "http:\/\/default\/admin\/config\/search\/redirect\/edit\/9?_format=hal_json"
        },
        "type": {
            "href": "http:\/\/drupal.org\/rest\/type\/redirect\/redirect"
        },
        "http:\/\/drupal.org\/rest\/relation\/redirect\/redirect\/uid": [
            {
                "href": "http:\/\/default\/user\/1?_format=hal_json"
            }
        ]
    },
    "rid": [
        {
            "value": 9
        }
    ],
    "uuid": [
        {
            "value": "a0bf0b85-d515-4cee-bc44-17574873261c"
        }
    ],
    "hash": [
        {
            "value": "Kgx4THNhqsxM0lhRzT9LvQuaEcGIOqorG91jFaQwduI"
        }
    ],
    "type": [
        {
            "value": "redirect"
        }
    ],
    "_embedded": {
        "http:\/\/drupal.org\/rest\/relation\/redirect\/redirect\/uid": [
            {
                "_links": {
                    "self": {
                        "href": "http:\/\/default\/user\/1?_format=hal_json"
                    },
                    "type": {
                        "href": "http:\/\/drupal.org\/rest\/type\/user\/user"
                    }
                },
                "uuid": [
                    {
                        "value": "4e7ef302-640e-4b23-ad78-67025c5d4e21"
                    }
                ]
            }
        ]
    },
    "redirect_source": [
        {
            "path": "donec-mattis-justo-est-porta-placerat-donec-ullamcorper-dui-nec-tristique-malesuada-purus-neque",
            "query": []
        }
    ],
    "redirect_redirect": [
        {
            "uri": "internal:\/node\/6",
            "title": null,
            "options": []
        }
    ],
    "language": [
        {
            "value": "und"
        }
    ],
    "status_code": [
        {
            "value": 301
        }
    ],
    "created": [
        {
            "value": "2019-07-22T14:49:54+00:00",
            "format": "Y-m-d\\TH:i:sP"
        }
    ]
}