{
    "_links": {
        "self": {
            "href": "http:\/\/default\/admin\/config\/search\/redirect\/edit\/47?_format=hal_json"
        },
        "type": {
            "href": "http:\/\/drupal.org\/rest\/type\/redirect\/redirect"
        },
        "http:\/\/drupal.org\/rest\/relation\/redirect\/redirect\/uid": [
            {
                "href": "http:\/\/default\/en\/user\/1?_format=hal_json"
            }
        ]
    },
    "rid": [
        {
            "value": 47
        }
    ],
    "uuid": [
        {
            "value": "a7fcbf4e-c759-403b-874a-44fa24beff2a"
        }
    ],
    "hash": [
        {
            "value": "Ov3hqEnNKuL_J-jNS4UptrE54m6G5Upb69jHYufaPFg"
        }
    ],
    "type": [
        {
            "value": "redirect"
        }
    ],
    "_embedded": {
        "http:\/\/drupal.org\/rest\/relation\/redirect\/redirect\/uid": [
            {
                "_links": {
                    "self": {
                        "href": "http:\/\/default\/en\/user\/1?_format=hal_json"
                    },
                    "type": {
                        "href": "http:\/\/drupal.org\/rest\/type\/user\/user"
                    }
                },
                "uuid": [
                    {
                        "value": "e864442b-eff6-43f7-81ca-301a536cf821"
                    }
                ]
            }
        ]
    },
    "redirect_source": [
        {
            "path": "aenean\/curabitur-iaculis-tortor-sit-amet-lacus-fringilla-sed-pellentesque-nisl-lobortis",
            "query": []
        }
    ],
    "redirect_redirect": [
        {
            "uri": "internal:\/node\/5",
            "title": null,
            "options": []
        }
    ],
    "language": [
        {
            "value": "und"
        }
    ],
    "status_code": [
        {
            "value": 301
        }
    ],
    "created": [
        {
            "value": "2020-01-15T09:26:01+00:00",
            "format": "Y-m-d\\TH:i:sP"
        }
    ]
}